tyled/__init__.py
tyled/command/__init__.py
tyled/tile.py
tyled/tileset/__init__.py
tyled/tileset/atlas/__init__.py
tyled/tileset/atlas/atlas.py
tyled/tileset/atlas/templates/tile.xml
tyled/tileset/collection/__init__.py
tyled/tileset/collection/collection.py
tyled/tileset/collection/templates/header.xml
tyled/tileset/collection/templates/tile.xml
tyled/tileset/factory.py
tyled/tileset/orthogonal/__init__.py
tyled/tileset/orthogonal/orthogonal.py
tyled/tileset/orthogonal/templates/tile.xml
tyled/tileset/templates/header.xml
tyled/tileset/templates/tile.xml
tyled/tileset/templates/tileset.xml
tyled/tileset/tileset.py
tyled/version.py
tyled-0.2.0.dist-info/entry_points.txt
tyled-0.2.0.dist-info/LICENSE
tyled-0.2.0.dist-info/WHEEL
tyled-0.2.0.dist-info/METADATA
tyled-0.2.0.dist-info/RECORD
