Metadata-Version: 2.1
Name: tyled
Version: 0.2.0
Summary: 
Author: Kurtis Fields
Author-email: kurtisfields@gmail.com
Requires-Python: >=3.8,<3.12
Classifier: Programming Language :: Python :: 3
Classifier: Programming Language :: Python :: 3.8
Classifier: Programming Language :: Python :: 3.9
Classifier: Programming Language :: Python :: 3.10
Classifier: Programming Language :: Python :: 3.11
Requires-Dist: click (>=8.1.3,<9.0.0)
Requires-Dist: jinja2 (>=3.1.2,<4.0.0)
Requires-Dist: pillow (>=9.3.0,<10.0.0)
Requires-Dist: rectpack (>=0.2.2,<0.3.0)
Requires-Dist: toml (>=0.10.2,<0.11.0)
